MANIFEST.in
README.rst
requirements.txt
setup.cfg
setup.py
pymessenger3/__init__.py
pymessenger3/airline.py
pymessenger3/bot.py
pymessenger3/buttons.py
pymessenger3/utils.py
pymessenger3.egg-info/PKG-INFO
pymessenger3.egg-info/SOURCES.txt
pymessenger3.egg-info/dependency_links.txt
pymessenger3.egg-info/requires.txt
pymessenger3.egg-info/top_level.txt